falcon_toolkit/__init__.py
falcon_toolkit/common/__init__.py
falcon_toolkit/common/auth.py
falcon_toolkit/common/auth_backends/__init__.py
falcon_toolkit/common/auth_backends/default.py
falcon_toolkit/common/auth_backends/public_mssp.py
falcon_toolkit/common/auth_backends/public_single_cid.py
falcon_toolkit/common/auth_backends/utils.py
falcon_toolkit/common/cli.py
falcon_toolkit/common/config.py
falcon_toolkit/common/console_utils.py
falcon_toolkit/common/constants.py
falcon_toolkit/common/logging_config.py
falcon_toolkit/common/meta.py
falcon_toolkit/common/namespace.py
falcon_toolkit/common/utils.py
falcon_toolkit/containment/__init__.py
falcon_toolkit/containment/cli.py
falcon_toolkit/containment/perform_containment.py
falcon_toolkit/falcon.py
falcon_toolkit/hosts/__init__.py
falcon_toolkit/hosts/cli.py
falcon_toolkit/hosts/host_search.py
falcon_toolkit/maintenance_token/__init__.py
falcon_toolkit/maintenance_token/cli.py
falcon_toolkit/maintenance_token/device_tokens.py
falcon_toolkit/policies/__init__.py
falcon_toolkit/policies/cli.py
falcon_toolkit/policies/constants.py
falcon_toolkit/policies/container.py
falcon_toolkit/policies/describe.py
falcon_toolkit/shell/__init__.py
falcon_toolkit/shell/cli.py
falcon_toolkit/shell/cmd_generators/__init__.py
falcon_toolkit/shell/cmd_generators/common.py
falcon_toolkit/shell/cmd_generators/reg.py
falcon_toolkit/shell/parsers.py
falcon_toolkit/shell/prompt.py
falcon_toolkit/shell/refresh.py
falcon_toolkit/shell/utils.py
falcon_toolkit/users/__init__.py
falcon_toolkit/users/cli.py
falcon_toolkit/users/user_management.py
falcon_toolkit-3.6.1.dist-info/LICENSE.md
falcon_toolkit-3.6.1.dist-info/METADATA
falcon_toolkit-3.6.1.dist-info/WHEEL
falcon_toolkit-3.6.1.dist-info/entry_points.txt
falcon_toolkit-3.6.1.dist-info/RECORD
