Metadata-Version: 2.3
Name: falcon-toolkit
Version: 3.6.1
Summary: Toolkit to interface with CrowdStrike Falcon via the API
License: MIT
Keywords: automation,cli,crowdstrike,endpoint-protection,falcon,falcon-platform
Author: Chris Hammond
Author-email: chris.hammond@crowdstrike.com
Requires-Python: >=3.9,<4.0
Classifier: License :: OSI Approved :: MIT License
Classifier: Natural Language :: English
Classifier: Operating System :: MacOS
Classifier: Operating System :: Microsoft :: Windows
Classifier: Operating System :: POSIX :: Linux
Classifier: Programming Language :: Python :: 3
Classifier: Programming Language :: Python :: 3.9
Classifier: Programming Language :: Python :: 3.10
Classifier: Programming Language :: Python :: 3.11
Classifier: Programming Language :: Python :: 3.12
Classifier: Programming Language :: Python :: 3.13
Classifier: Programming Language :: Python :: 3 :: Only
Classifier: Topic :: Security
Classifier: Topic :: System :: Shells
Classifier: Topic :: Terminals
Requires-Dist: caracara (>=1.0.1,<2.0.0)
Requires-Dist: click (>=8.1.3,<9.0.0)
Requires-Dist: click-option-group (>=0.5.6,<0.6.0)
Requires-Dist: click-spinner (>=0.1.10,<0.2.0)
Requires-Dist: cmd2 (>=2.4,<3.0)
Requires-Dist: colorama (>=0.4.5,<0.5.0)
Requires-Dist: keyring (>=24,<26)
Requires-Dist: platformdirs (>=4.2.0,<5.0.0)
Requires-Dist: prompt-toolkit (>=3.0.43,<4.0.0)
Requires-Dist: tabulate (>=0.9.0,<0.10.0)
Project-URL: Repository, http://github.com/CrowdStrike/Falcon-Toolkit
